rsdb_utils/__init__.py
rsdb_utils/utils.py
rsdb_utils/rsdb-schema/case_study_schema.json
rsdb_utils-0.5.dist-info/LICENCE.txt
rsdb_utils-0.5.dist-info/METADATA
rsdb_utils-0.5.dist-info/WHEEL
rsdb_utils-0.5.dist-info/top_level.txt
rsdb_utils-0.5.dist-info/RECORD
