Metadata-Version: 2.1
Name: rsdb-utils
Version: 0.5
Summary: Utils to process the Regime Shifts DataBase CSV and parquet files
Author-email: Romain Thomas <romain.thomas@su.se>
License: GNU GENERAL PUBLIC LICENSE
Project-URL: Homepage, https://github.com/regimeshifts/rsdb-utils
Project-URL: Project website, https://www.regimeshifts.org/
Keywords: Regime Shifts,Regime Shifts DataBase,RSDB,Ecosystems,Ecology,Social-ecological systems,Data analysis,Scientific research
Classifier: Development Status :: 3 - Alpha
Classifier: License :: OSI Approved :: GNU General Public License v3 (GPLv3)
Classifier: Programming Language :: Python
Classifier: Programming Language :: Python :: 3
Classifier: Intended Audience :: Science/Research
Classifier: Topic :: Database
Classifier: Topic :: File Formats :: JSON :: JSON Schema
Classifier: Topic :: Utilities
Requires-Python: >=3.9
License-File: LICENCE.txt
Requires-Dist: pandas >=2.1
Requires-Dist: jsonref >=1.1
Requires-Dist: jsonschema >=4.22
Requires-Dist: tqdm >=4.50
Requires-Dist: pyarrow
